python_auditor-0.10.0.dist-info/METADATA
python_auditor-0.10.0.dist-info/WHEEL
pyauditor/__init__.py
pyauditor/pyauditor.cpython-313-x86_64-linux-gnu.so
python_auditor-0.10.0.dist-info/RECORD
