Metadata-Version: 2.1
Name: python-auditor
Version: 0.10.0
Classifier: Programming Language :: Rust
Classifier: Programming Language :: Python :: Implementation :: CPython
Classifier: Development Status :: 3 - Alpha
Classifier: Intended Audience :: Developers
Classifier: Intended Audience :: Information Technology
Classifier: Intended Audience :: Science/Research
Classifier: Intended Audience :: System Administrators
Classifier: License :: OSI Approved :: MIT License
Classifier: License :: OSI Approved :: Apache Software License
Summary: Python interface to AuditorClient
Keywords: accounting,opportunistic,grid-computing,batch-systems
Home-Page: https://alu-schumacher.github.io/AUDITOR/
Author: Stefan Kroboth <stefan.kroboth@gmail.com>
Author-email: Stefan Kroboth <stefan.kroboth@gmail.com>
License: MIT OR Apache-2.0
Requires-Python: >=3.9
Project-URL: Source Code, https://github.com/alu-schumacher/AUDITOR
